[
  {
    "topic_id": 0,
    "words": [
      [
        "penjualan",
        0.031036479398608208
      ],
      [
        "biaya",
        0.02631765604019165
      ],
      [
        "produksi",
        0.021701864898204803
      ],
      [
        "produk",
        0.01712474599480629
      ],
      [
        "pengendalian",
        0.014146077446639538
      ],
      [
        "persediaan",
        0.009509977884590626
      ],
      [
        "bahan_baku",
        0.0077628884464502335
      ],
      [
        "barang",
        0.007708834018558264
      ],
      [
        "sistem",
        0.0076515693217515945
      ],
      [
        "aktivitas",
        0.007571511436253786
      ],
      [
        "perencanaan",
        0.007540148217231035
      ],
      [
        "biaya_produksi",
        0.006540389731526375
      ],
      [
        "mesin",
        0.005712918471544981
      ],
      [
        "kualitas",
        0.005176194477826357
      ],
      [
        "memadai",
        0.004933633375912905
      ],
      [
        "sistem_informasi",
        0.0048925625160336494
      ],
      [
        "harga_pokok",
        0.004526077304035425
      ],
      [
        "menentukan",
        0.004512814339250326
      ],
      [
        "menghasilkan",
        0.004456758499145508
      ],
      [
        "standar",
        0.004113803151994944
      ]
    ],
    "label": "Topic 0: penjualan, biaya, produksi",
    "coherence": 0.0,
    "top_words": [
      "penjualan",
      "biaya",
      "produksi",
      "produk",
      "pengendalian",
      "persediaan",
      "bahan_baku",
      "barang",
      "sistem",
      "aktivitas",
      "perencanaan",
      "biaya_produksi",
      "mesin",
      "kualitas",
      "memadai",
      "sistem_informasi",
      "harga_pokok",
      "menentukan",
      "menghasilkan",
      "standar"
    ]
  },
  {
    "topic_id": 1,
    "words": [
      [
        "karyawan",
        0.07329768687486649
      ],
      [
        "kinerja_karyawan",
        0.04709120839834213
      ],
      [
        "kinerja",
        0.02649887278676033
      ],
      [
        "disiplin_kerja",
        0.02153920941054821
      ],
      [
        "pegawai",
        0.02075464464724064
      ],
      [
        "motivasi",
        0.020282654091715813
      ],
      [
        "motivasi_kerja",
        0.01770840585231781
      ],
      [
        "kerja",
        0.017611199989914894
      ],
      [
        "kompensasi",
        0.014294663444161415
      ],
      [
        "lingkungan_kerja",
        0.013950200751423836
      ],
      [
        "pelatihan",
        0.0130371805280447
      ],
      [
        "gaya_kepemimpinan",
        0.013000057078897953
      ],
      [
        "manusia",
        0.010848676785826683
      ],
      [
        "kepuasan_kerja",
        0.010843048803508282
      ],
      [
        "sumber_daya",
        0.010733600705862045
      ],
      [
        "prestasi_kerja",
        0.00971201527863741
      ],
      [
        "organisasi",
        0.008357570506632328
      ],
      [
        "kompetensi",
        0.007027594372630119
      ],
      [
        "verifikatif",
        0.005586700048297644
      ],
      [
        "budaya_organisasi",
        0.005459754262119532
      ]
    ],
    "label": "Topic 1: karyawan, kinerja_karyawan, kinerja",
    "coherence": 0.0,
    "top_words": [
      "karyawan",
      "kinerja_karyawan",
      "kinerja",
      "disiplin_kerja",
      "pegawai",
      "motivasi",
      "motivasi_kerja",
      "kerja",
      "kompensasi",
      "lingkungan_kerja",
      "pelatihan",
      "gaya_kepemimpinan",
      "manusia",
      "kepuasan_kerja",
      "sumber_daya",
      "prestasi_kerja",
      "organisasi",
      "kompetensi",
      "verifikatif",
      "budaya_organisasi"
    ]
  },
  {
    "topic_id": 2,
    "words": [
      [
        "modal_kerja",
        0.022546028718352318
      ],
      [
        "pendapatan_asli",
        0.021833475679159164
      ],
      [
        "kerja",
        0.02082458697259426
      ],
      [
        "hotel",
        0.01830052211880684
      ],
      [
        "koperasi",
        0.016398312523961067
      ],
      [
        "piutang",
        0.012810648418962955
      ],
      [
        "pemerintah",
        0.010139885358512402
      ],
      [
        "lapangan",
        0.010032154619693756
      ],
      [
        "belanja",
        0.009613941423594952
      ],
      [
        "program",
        0.00751076964661479
      ],
      [
        "sumber",
        0.007319826632738113
      ],
      [
        "pad",
        0.007108672987669706
      ],
      [
        "sumber_penggunaan",
        0.007054571993649006
      ],
      [
        "modal",
        0.006884440314024687
      ],
      [
        "jepang",
        0.006345455069094896
      ],
      [
        "perputaran_piutang",
        0.005419125780463219
      ],
      [
        "pertumbuhan_ekonomi",
        0.005338877439498901
      ],
      [
        "tugas",
        0.005337805021554232
      ],
      [
        "likuiditas",
        0.005116765853017569
      ],
      [
        "bahasa_jepang",
        0.005067151505500078
      ]
    ],
    "label": "Topic 2: modal_kerja, pendapatan_asli, kerja",
    "coherence": 0.0,
    "top_words": [
      "modal_kerja",
      "pendapatan_asli",
      "kerja",
      "hotel",
      "koperasi",
      "piutang",
      "pemerintah",
      "lapangan",
      "belanja",
      "program",
      "sumber",
      "pad",
      "sumber_penggunaan",
      "modal",
      "jepang",
      "perputaran_piutang",
      "pertumbuhan_ekonomi",
      "tugas",
      "likuiditas",
      "bahasa_jepang"
    ]
  },
  {
    "topic_id": 3,
    "words": [
      [
        "sistem",
        0.023786885663866997
      ],
      [
        "aplikasi",
        0.023577028885483742
      ],
      [
        "informasi",
        0.017575964331626892
      ],
      [
        "media",
        0.01126084104180336
      ],
      [
        "perancangan",
        0.008553748019039631
      ],
      [
        "penggunaan",
        0.007242162711918354
      ],
      [
        "jaringan",
        0.007076534908264875
      ],
      [
        "teknologi",
        0.006612077355384827
      ],
      [
        "layanan",
        0.006309160031378269
      ],
      [
        "umkm",
        0.006086047738790512
      ],
      [
        "internet",
        0.005836117547005415
      ],
      [
        "digital",
        0.005832416471093893
      ],
      [
        "video",
        0.005564529448747635
      ],
      [
        "game",
        0.005295880138874054
      ],
      [
        "air",
        0.0052345977164804935
      ],
      [
        "berbasis",
        0.005047123413532972
      ],
      [
        "online",
        0.005025978200137615
      ],
      [
        "bentuk",
        0.004904004745185375
      ],
      [
        "algoritma",
        0.004898598417639732
      ],
      [
        "desain",
        0.004785377997905016
      ]
    ],
    "label": "Topic 3: sistem, aplikasi, informasi",
    "coherence": 0.0,
    "top_words": [
      "sistem",
      "aplikasi",
      "informasi",
      "media",
      "perancangan",
      "penggunaan",
      "jaringan",
      "teknologi",
      "layanan",
      "umkm",
      "internet",
      "digital",
      "video",
      "game",
      "air",
      "berbasis",
      "online",
      "bentuk",
      "algoritma",
      "desain"
    ]
  },
  {
    "topic_id": 4,
    "words": [
      [
        "profitabilitas",
        0.016547756269574165
      ],
      [
        "bursa_efek",
        0.012154322117567062
      ],
      [
        "independen",
        0.010017250664532185
      ],
      [
        "ukuran",
        0.009728369303047657
      ],
      [
        "roa",
        0.009412327781319618
      ],
      [
        "kepatuhan_wajib",
        0.007746732793748379
      ],
      [
        "sampling",
        0.007555870804935694
      ],
      [
        "purposive_sampling",
        0.007490098476409912
      ],
      [
        "non_performing",
        0.006872416473925114
      ],
      [
        "kebijakan_dividen",
        0.006674530450254679
      ],
      [
        "ldr",
        0.0063172271475195885
      ],
      [
        "kepemilikan_institusional",
        0.006216672249138355
      ],
      [
        "wajib_pajak",
        0.006059886422008276
      ],
      [
        "car",
        0.006032697390764952
      ],
      [
        "diuji",
        0.005972541403025389
      ],
      [
        "regresi_linear",
        0.005914817098528147
      ],
      [
        "pajak",
        0.005904552061110735
      ],
      [
        "pajak_pribadi",
        0.005686862859874964
      ],
      [
        "leverage",
        0.005412031430751085
      ],
      [
        "bank",
        0.00510040670633316
      ]
    ],
    "label": "Topic 4: profitabilitas, bursa_efek, independen",
    "coherence": 0.0,
    "top_words": [
      "profitabilitas",
      "bursa_efek",
      "independen",
      "ukuran",
      "roa",
      "kepatuhan_wajib",
      "sampling",
      "purposive_sampling",
      "non_performing",
      "kebijakan_dividen",
      "ldr",
      "kepemilikan_institusional",
      "wajib_pajak",
      "car",
      "diuji",
      "regresi_linear",
      "pajak",
      "pajak_pribadi",
      "leverage",
      "bank"
    ]
  },
  {
    "topic_id": 5,
    "words": [
      [
        "pajak",
        0.05762095004320145
      ],
      [
        "wajib_pajak",
        0.02527414634823799
      ],
      [
        "penerimaan_pajak",
        0.021222790703177452
      ],
      [
        "kas",
        0.02079872600734234
      ],
      [
        "pendapatan",
        0.018165767192840576
      ],
      [
        "kepatuhan_wajib",
        0.017675237730145454
      ],
      [
        "anggaran",
        0.017201825976371765
      ],
      [
        "badan",
        0.011226107366383076
      ],
      [
        "negara",
        0.01035388559103012
      ],
      [
        "kantor_pelayanan",
        0.009716199710965157
      ],
      [
        "perpajakan",
        0.009427712298929691
      ],
      [
        "pajak_penghasilan",
        0.008872385136783123
      ],
      [
        "pemerintah",
        0.008774751797318459
      ],
      [
        "penerimaan",
        0.007376976776868105
      ],
      [
        "penyusunan_anggaran",
        0.007332474924623966
      ],
      [
        "pajak_pratama",
        0.006541892420500517
      ],
      [
        "pembayaran",
        0.006003492046147585
      ],
      [
        "pemeriksaan_pajak",
        0.00595376081764698
      ],
      [
        "kontribusi",
        0.005731072276830673
      ],
      [
        "sumber",
        0.005595920141786337
      ]
    ],
    "label": "Topic 5: pajak, wajib_pajak, penerimaan_pajak",
    "coherence": 0.0,
    "top_words": [
      "pajak",
      "wajib_pajak",
      "penerimaan_pajak",
      "kas",
      "pendapatan",
      "kepatuhan_wajib",
      "anggaran",
      "badan",
      "negara",
      "kantor_pelayanan",
      "perpajakan",
      "pajak_penghasilan",
      "pemerintah",
      "penerimaan",
      "penyusunan_anggaran",
      "pajak_pratama",
      "pembayaran",
      "pemeriksaan_pajak",
      "kontribusi",
      "sumber"
    ]
  },
  {
    "topic_id": 6,
    "words": [
      [
        "karyawan",
        0.02988402731716633
      ],
      [
        "proyek",
        0.014473188668489456
      ],
      [
        "karya",
        0.014119305647909641
      ],
      [
        "film",
        0.012306958436965942
      ],
      [
        "gaya_kepemimpinan",
        0.010941971093416214
      ],
      [
        "produktivitas_kerja",
        0.010714223608374596
      ],
      [
        "fungsi",
        0.008150715380907059
      ],
      [
        "aktiva",
        0.007761871442198753
      ],
      [
        "strategi",
        0.00772889843210578
      ],
      [
        "promosi_jabatan",
        0.007641573436558247
      ],
      [
        "bentuk",
        0.0074136215262115
      ],
      [
        "sosial",
        0.00736958347260952
      ],
      [
        "perspektif",
        0.006981592625379562
      ],
      [
        "tindak",
        0.0068605518899858
      ],
      [
        "arus_kas",
        0.006796960718929768
      ],
      [
        "penggunaan",
        0.006636767648160458
      ],
      [
        "kalimat",
        0.006620845757424831
      ],
      [
        "novel",
        0.006553859915584326
      ],
      [
        "kinerja",
        0.006263920571655035
      ],
      [
        "mengidentifikasi",
        0.005876938812434673
      ]
    ],
    "label": "Topic 6: karyawan, proyek, karya",
    "coherence": 0.0,
    "top_words": [
      "karyawan",
      "proyek",
      "karya",
      "film",
      "gaya_kepemimpinan",
      "produktivitas_kerja",
      "fungsi",
      "aktiva",
      "strategi",
      "promosi_jabatan",
      "bentuk",
      "sosial",
      "perspektif",
      "tindak",
      "arus_kas",
      "penggunaan",
      "kalimat",
      "novel",
      "kinerja",
      "mengidentifikasi"
    ]
  },
  {
    "topic_id": 7,
    "words": [
      [
        "keuangan",
        0.10532761365175247
      ],
      [
        "kinerja",
        0.05326823890209198
      ],
      [
        "bank",
        0.018513040617108345
      ],
      [
        "informasi",
        0.012614808976650238
      ],
      [
        "kondisi",
        0.007679841015487909
      ],
      [
        "lingkungan",
        0.0061118220910429955
      ],
      [
        "pemerintah",
        0.0059449332766234875
      ],
      [
        "investasi",
        0.005565452389419079
      ],
      [
        "syariah",
        0.005344829987734556
      ],
      [
        "dana",
        0.005132897756993771
      ],
      [
        "bank_syariah",
        0.0051046740263700485
      ],
      [
        "pengambilan_keputusan",
        0.004988744854927063
      ],
      [
        "aktivitas",
        0.004914737306535244
      ],
      [
        "profitabilitas",
        0.004826207645237446
      ],
      [
        "aset",
        0.004807746037840843
      ],
      [
        "telekomunikasi",
        0.004451338201761246
      ],
      [
        "kemampuan",
        0.004344307351857424
      ],
      [
        "menilai_kinerja",
        0.004171171225607395
      ],
      [
        "eva",
        0.004017637111246586
      ],
      [
        "likuiditas",
        0.003872693283483386
      ]
    ],
    "label": "Topic 7: keuangan, kinerja, bank",
    "coherence": 0.0,
    "top_words": [
      "keuangan",
      "kinerja",
      "bank",
      "informasi",
      "kondisi",
      "lingkungan",
      "pemerintah",
      "investasi",
      "syariah",
      "dana",
      "bank_syariah",
      "pengambilan_keputusan",
      "aktivitas",
      "profitabilitas",
      "aset",
      "telekomunikasi",
      "kemampuan",
      "menilai_kinerja",
      "eva",
      "likuiditas"
    ]
  },
  {
    "topic_id": 8,
    "words": [
      [
        "audit_internal",
        0.025817494839429855
      ],
      [
        "pengendalian_internal",
        0.02232414111495018
      ],
      [
        "audit",
        0.021273477002978325
      ],
      [
        "kualitas",
        0.021091138944029808
      ],
      [
        "internal",
        0.0189594104886055
      ],
      [
        "pemerintah",
        0.018852977082133293
      ],
      [
        "sistem",
        0.015975965186953545
      ],
      [
        "auditor",
        0.013946264050900936
      ],
      [
        "governance",
        0.013520251028239727
      ],
      [
        "keuangan",
        0.013410515151917934
      ],
      [
        "efektivitas",
        0.01279523316770792
      ],
      [
        "good_corporate",
        0.012718901969492435
      ],
      [
        "kinerja",
        0.012028556317090988
      ],
      [
        "auditor_internal",
        0.011408369056880474
      ],
      [
        "pengendalian_intern",
        0.009094997309148312
      ],
      [
        "memadai",
        0.008180339820683002
      ],
      [
        "kuesioner",
        0.0074200015515089035
      ],
      [
        "independen",
        0.007367131300270557
      ],
      [
        "kecurangan",
        0.0071398974396288395
      ],
      [
        "efektivitas_pengendalian",
        0.005664531607180834
      ]
    ],
    "label": "Topic 8: audit_internal, pengendalian_internal, audit",
    "coherence": 0.0,
    "top_words": [
      "audit_internal",
      "pengendalian_internal",
      "audit",
      "kualitas",
      "internal",
      "pemerintah",
      "sistem",
      "auditor",
      "governance",
      "keuangan",
      "efektivitas",
      "good_corporate",
      "kinerja",
      "auditor_internal",
      "pengendalian_intern",
      "memadai",
      "kuesioner",
      "independen",
      "kecurangan",
      "efektivitas_pengendalian"
    ]
  },
  {
    "topic_id": 9,
    "words": [
      [
        "sistem_informasi",
        0.024863634258508682
      ],
      [
        "sistem",
        0.020153891295194626
      ],
      [
        "karyawan",
        0.012818465940654278
      ],
      [
        "informasi",
        0.012080431915819645
      ],
      [
        "manusia",
        0.010425062850117683
      ],
      [
        "sumber_daya",
        0.009862815961241722
      ],
      [
        "pegawai",
        0.009393548592925072
      ],
      [
        "sesuai",
        0.00807657279074192
      ],
      [
        "aplikasi",
        0.008042734116315842
      ],
      [
        "rekrutmen",
        0.007436356972903013
      ],
      [
        "tugas",
        0.006880813743919134
      ],
      [
        "program",
        0.006636589765548706
      ],
      [
        "pengembangan",
        0.005752359051257372
      ],
      [
        "organisasi",
        0.005548899527639151
      ],
      [
        "kerja",
        0.004966243170201778
      ],
      [
        "gaji",
        0.004948287270963192
      ],
      [
        "pekerjaan",
        0.004523358773440123
      ],
      [
        "seleksi",
        0.004384052939713001
      ],
      [
        "penggajian",
        0.004297328647226095
      ],
      [
        "hambatan",
        0.00414445623755455
      ]
    ],
    "label": "Topic 9: sistem_informasi, sistem, karyawan",
    "coherence": 0.0,
    "top_words": [
      "sistem_informasi",
      "sistem",
      "karyawan",
      "informasi",
      "manusia",
      "sumber_daya",
      "pegawai",
      "sesuai",
      "aplikasi",
      "rekrutmen",
      "tugas",
      "program",
      "pengembangan",
      "organisasi",
      "kerja",
      "gaji",
      "pekerjaan",
      "seleksi",
      "penggajian",
      "hambatan"
    ]
  },
  {
    "topic_id": 10,
    "words": [
      [
        "harga_saham",
        0.03267776593565941
      ],
      [
        "saham",
        0.02244214341044426
      ],
      [
        "bursa_efek",
        0.020790956914424896
      ],
      [
        "laba",
        0.01913464441895485
      ],
      [
        "return_saham",
        0.013475915417075157
      ],
      [
        "profitabilitas",
        0.012614211067557335
      ],
      [
        "investasi",
        0.010575037449598312
      ],
      [
        "investor",
        0.010046121664345264
      ],
      [
        "model",
        0.009323765523731709
      ],
      [
        "earning_share",
        0.009192531928420067
      ],
      [
        "bei",
        0.008823912590742111
      ],
      [
        "return_equity",
        0.008777684532105923
      ],
      [
        "keuangan",
        0.008199494332075119
      ],
      [
        "efek",
        0.007775434292852879
      ],
      [
        "debt_equity",
        0.007539988029748201
      ],
      [
        "statistik",
        0.0073426272720098495
      ],
      [
        "arus_kas",
        0.0071373311802744865
      ],
      [
        "signifikansi",
        0.007100560236722231
      ],
      [
        "sampling",
        0.006126359570771456
      ],
      [
        "sekunder",
        0.006053003016859293
      ]
    ],
    "label": "Topic 10: harga_saham, saham, bursa_efek",
    "coherence": 0.0,
    "top_words": [
      "harga_saham",
      "saham",
      "bursa_efek",
      "laba",
      "return_saham",
      "profitabilitas",
      "investasi",
      "investor",
      "model",
      "earning_share",
      "bei",
      "return_equity",
      "keuangan",
      "efek",
      "debt_equity",
      "statistik",
      "arus_kas",
      "signifikansi",
      "sampling",
      "sekunder"
    ]
  },
  {
    "topic_id": 11,
    "words": [
      [
        "konsumen",
        0.04033278673887253
      ],
      [
        "keputusan_pembelian",
        0.02503904327750206
      ],
      [
        "produk",
        0.022528721019625664
      ],
      [
        "kualitas_pelayanan",
        0.01971416547894478
      ],
      [
        "harga",
        0.014586553908884525
      ],
      [
        "jasa",
        0.013747191056609154
      ],
      [
        "kredit",
        0.012316707521677017
      ],
      [
        "promosi",
        0.011131816543638706
      ],
      [
        "kualitas_produk",
        0.010942105203866959
      ],
      [
        "minat_beli",
        0.01080445945262909
      ],
      [
        "store_atmosphere",
        0.009473420679569244
      ],
      [
        "pelanggan",
        0.009067936800420284
      ],
      [
        "bank",
        0.008246203884482384
      ],
      [
        "brand_image",
        0.007941817864775658
      ],
      [
        "kualitas",
        0.007253499701619148
      ],
      [
        "loyalitas_konsumen",
        0.007127922959625721
      ],
      [
        "pemberian_kredit",
        0.007012525573372841
      ],
      [
        "pelayanan",
        0.006924610119313002
      ],
      [
        "kepuasan_konsumen",
        0.006844710558652878
      ],
      [
        "loyalitas_pelanggan",
        0.006764320656657219
      ]
    ],
    "label": "Topic 11: konsumen, keputusan_pembelian, produk",
    "coherence": 0.0,
    "top_words": [
      "konsumen",
      "keputusan_pembelian",
      "produk",
      "kualitas_pelayanan",
      "harga",
      "jasa",
      "kredit",
      "promosi",
      "kualitas_produk",
      "minat_beli",
      "store_atmosphere",
      "pelanggan",
      "bank",
      "brand_image",
      "kualitas",
      "loyalitas_konsumen",
      "pemberian_kredit",
      "pelayanan",
      "kepuasan_konsumen",
      "loyalitas_pelanggan"
    ]
  }
]